unseal_vault/__init__.py
unseal_vault/cli.py
unseal_vault/consul.py
unseal_vault/op_v4.py
unseal_vault/pass.py
unseal_vault/run.py
unseal_vault/vault.py
unseal_vault-0.2.3.dist-info/METADATA
unseal_vault-0.2.3.dist-info/WHEEL
unseal_vault-0.2.3.dist-info/entry_points.txt
unseal_vault-0.2.3.dist-info/RECORD
