Metadata-Version: 2.1
Name: unseal-vault
Version: 0.2.3
Summary: Python helper for unseal `Vault.io <http://vaultproject.io/>`
License: AGPL
Author: Nicolas Ledez
Author-email: github.public@ledez.net
Requires-Python: >=3.8,<4.0
Classifier: License :: Other/Proprietary License
Classifier: Programming Language :: Python :: 3
Classifier: Programming Language :: Python :: 3.8
Classifier: Programming Language :: Python :: 3.9
Classifier: Programming Language :: Python :: 3.10
Classifier: Programming Language :: Python :: 3.11
Classifier: Programming Language :: Python :: 3.12
Requires-Dist: PySocks (>=1.7.1,<2.0.0)
Requires-Dist: PyYAML (>=6.0,<7.0)
Requires-Dist: hvac (>=1.2.1,<2.0.0)
Requires-Dist: python-consul (>=1.1.0,<2.0.0)
